aaaarg
