Metadata-Version: 1.1
Name: aaaarg-python
Version: 0.12
Summary: Python interface for aaaarg
Home-page: http://github.com/metadada/aaaarg-python
Author: metadada
Author-email: metadadametadada@gmail.com
License: GPL3
Platform: UNKNOWN
Classifier: Operating System :: OS Independent
Classifier: Programming Language :: Python
Classifier: Programming Language :: Python :: 2
Classifier: Programming Language :: Python :: 2.7
Classifier: Programming Language :: Python :: 3
Classifier: Programming Language :: Python :: 3.4
Classifier: Programming Language :: Python :: 3.5
Classifier: Topic :: Software Development :: Libraries :: Python Modules
